landcalc/__init__.py
landcalc/analysis.py
landcalc/common.py
landcalc/foliumap.py
landcalc/landcalc.py
landcalc/registry.py
landcalc/ui.py
landcalc-0.0.4.dist-info/licenses/LICENSE
landcalc-0.0.4.dist-info/METADATA
landcalc-0.0.4.dist-info/WHEEL
landcalc-0.0.4.dist-info/entry_points.txt
landcalc-0.0.4.dist-info/top_level.txt
landcalc-0.0.4.dist-info/RECORD
